LICENSE
README.md
setup.py
AnnotatedSentence/AnnotatedCorpus.c
AnnotatedSentence/AnnotatedCorpus.pxd
AnnotatedSentence/AnnotatedCorpus.pyx
AnnotatedSentence/AnnotatedPhrase.c
AnnotatedSentence/AnnotatedPhrase.pxd
AnnotatedSentence/AnnotatedPhrase.pyx
AnnotatedSentence/AnnotatedSentence.c
AnnotatedSentence/AnnotatedSentence.pxd
AnnotatedSentence/AnnotatedSentence.pyx
AnnotatedSentence/AnnotatedWord.c
AnnotatedSentence/AnnotatedWord.pxd
AnnotatedSentence/AnnotatedWord.pyx
AnnotatedSentence/LanguageType.py
AnnotatedSentence/ViewLayerType.py
AnnotatedSentence/__init__.py
NlpToolkit_AnnotatedSentence_Cy.egg-info/PKG-INFO
NlpToolkit_AnnotatedSentence_Cy.egg-info/SOURCES.txt
NlpToolkit_AnnotatedSentence_Cy.egg-info/dependency_links.txt
NlpToolkit_AnnotatedSentence_Cy.egg-info/requires.txt
NlpToolkit_AnnotatedSentence_Cy.egg-info/top_level.txt
nlptoolkit_annotatedsentence_cy.egg-info/PKG-INFO
nlptoolkit_annotatedsentence_cy.egg-info/SOURCES.txt
nlptoolkit_annotatedsentence_cy.egg-info/dependency_links.txt
nlptoolkit_annotatedsentence_cy.egg-info/requires.txt
nlptoolkit_annotatedsentence_cy.egg-info/top_level.txt