Metadata-Version: 2.4
Name: nlptoolkit-annotatedsentence-cy
Version: 1.0.24
Summary: Annotated Sentence Processing Library
Home-page: https://github.com/StarlangSoftware/AnnotatedSentence-Cy
Author: olcaytaner
Author-email: olcay.yildiz@ozyegin.edu.tr
License-File: LICENSE
Requires-Dist: NlpToolkit-WordNet-Cy
Requires-Dist: NlpToolkit-NamedEntityRecognition-Cy
Requires-Dist: NlpToolkit-PropBank-Cy
Requires-Dist: NlpToolkit-DependencyParser-Cy
Requires-Dist: NlpToolkit-SentiNet-Cy
Requires-Dist: NlpToolkit-FrameNet-Cy
Dynamic: author
Dynamic: author-email
Dynamic: description
Dynamic: description-content-type
Dynamic: home-page
Dynamic: license-file
Dynamic: requires-dist
Dynamic: summary
